<templateSet group="Kotlin">
  <template name="region" value="// region $NAME$&#10;    $END$&#10;// endregion" description="Creates a region with a given name" toReformat="false" toShortenFQNames="true">
    <variable name="NAME" expression="" defaultValue="" alwaysStopAt="true" />
    <context>
      <option name="JAVA_STATEMENT" value="true" />
      <option name="KOTLIN_CLASS" value="true" />
      <option name="KOTLIN_STATEMENT" value="true" />
      <option name="KOTLIN_TOPLEVEL" value="true" />
    </context>
  </template>
</templateSet>